biopyflow/__init__.py
biopyflow/core/channel.py
biopyflow/core/config.py
biopyflow/core/flow.py
biopyflow/core/inout.py
biopyflow/core/step.py
biopyflow/pipeline/rnaseq.py
biopyflow-0.0.1.dist-info/METADATA
biopyflow-0.0.1.dist-info/WHEEL
biopyflow-0.0.1.dist-info/RECORD
