Metadata-Version: 2.4
Name: biopyflow
Version: 0.0.1
Summary: A simple workflow Management System for Bioinformatics in python
Project-URL: Repository, https://github.com/khoa-yelo/Biopyflow
Author-email: Khoa Hoang <pkhoang99@stanford.edu>, Adrian Juarez <adriancastaneda.j@gmail.com>
Maintainer-email: Khoa Hoang <pkhoang99@stanford.edu>, Adrian Juarez <adriancastaneda.j@gmail.com>
License-Expression: GPL-3.0-or-later
Keywords: Bioinformatics,Python
Classifier: License :: OSI Approved :: GNU General Public License v3 or later (GPLv3+)
Classifier: Programming Language :: Python :: 3
Classifier: Programming Language :: Python :: 3.14
Classifier: Topic :: Scientific/Engineering :: Bio-Informatics
Requires-Python: >=3.14
Requires-Dist: numpy>=2.0
Requires-Dist: pandas>=2.3
